akkits/__init__.py
akkits/receivers.py
akkits/senders.py
akkits/version.py
akkits/schema/__init__.py
akkits/schema/health_status/AlgoStatus.py
akkits/schema/health_status/DeviceStatus.py
akkits/schema/health_status/HealthStatus.py
akkits/schema/health_status/SensorStatus.py
akkits/schema/health_status/health_status.fbs
akkits/schema/health_status/message.py
akkits/schema/point_cloud/AttrType.py
akkits/schema/point_cloud/PointCloud.py
akkits/schema/point_cloud/PointCloudPacket.py
akkits/schema/point_cloud/message.py
akkits/schema/point_cloud/point_cloud_data.fbs
akkits/schema/tracklet_packet/BoundingBox.py
akkits/schema/tracklet_packet/ClassType.py
akkits/schema/tracklet_packet/Tracklet.py
akkits/schema/tracklet_packet/TrackletsPacket.py
akkits/schema/tracklet_packet/Vector3.py
akkits/schema/tracklet_packet/message.py
akkits/schema/tracklet_packet/tracklet_packet.fbs
akkits/scripts/examples/receiver_health.py
akkits/scripts/examples/receiver_point_cloud.py
akkits/scripts/examples/receiver_tracklet.py
akkits/scripts/examples/receiver_tracklet_health.py
akkits/scripts/examples/sender_health.py
akkits/scripts/examples/sender_point_cloud.py
akkits/scripts/examples/sender_tracklet.py
akkits/scripts/mock/faulty_fusion_controller.py
akkits/scripts/mock/faulty_lidar.py
akkits/scripts/mock/replay_tracklets.py
akkits/scripts/mock/sample_data/sample_tracklet.pkl
akkits/scripts/tools/record_point_cloud.py
akkits/scripts/tools/record_tracklet.py
akkits/utils/__init__.py
akkits/utils/flatbuffer.py
akkits/utils/io.py
akkits/utils/zmq.py
akkits-1.2.1.dist-info/METADATA
akkits-1.2.1.dist-info/WHEEL
akkits-1.2.1.dist-info/entry_points.txt
akkits-1.2.1.dist-info/top_level.txt
akkits-1.2.1.dist-info/RECORD
